maliba_ai/__init__.py
maliba_ai/config/__init__.py
maliba_ai/config/settings.py
maliba_ai/config/speakers.py
maliba_ai/models/__init__.py
maliba_ai/models/models.py
maliba_ai/sparktts/__init__.py
maliba_ai/sparktts/models/__init__.py
maliba_ai/sparktts/models/audio_tokenizer.py
maliba_ai/sparktts/models/bicodec.py
maliba_ai/sparktts/modules/__init__.py
maliba_ai/sparktts/modules/blocks/__init__.py
maliba_ai/sparktts/modules/blocks/layers.py
maliba_ai/sparktts/modules/blocks/samper.py
maliba_ai/sparktts/modules/blocks/vocos.py
maliba_ai/sparktts/modules/encoder_decoder/__init__.py
maliba_ai/sparktts/modules/encoder_decoder/feat_decoder.py
maliba_ai/sparktts/modules/encoder_decoder/feat_encoder.py
maliba_ai/sparktts/modules/encoder_decoder/wave_generator.py
maliba_ai/sparktts/modules/fsq/__init__.py
maliba_ai/sparktts/modules/fsq/finite_scalar_quantization.py
maliba_ai/sparktts/modules/fsq/residual_fsq.py
maliba_ai/sparktts/modules/speaker/__init__.py
maliba_ai/sparktts/modules/speaker/ecapa_tdnn.py
maliba_ai/sparktts/modules/speaker/perceiver_encoder.py
maliba_ai/sparktts/modules/speaker/pooling_layers.py
maliba_ai/sparktts/modules/speaker/speaker_encoder.py
maliba_ai/sparktts/modules/vq/__init__.py
maliba_ai/sparktts/modules/vq/factorized_vector_quantize.py
maliba_ai/sparktts/utils/__init__.py
maliba_ai/sparktts/utils/audio.py
maliba_ai/sparktts/utils/file.py
maliba_ai/sparktts/utils/token_parser.py
maliba_ai/tts/__init__.py
maliba_ai/tts/inference.py
maliba_ai/utils/__init__.py
maliba_ai/utils/exceptions.py
maliba_ai/utils/utils.py
maliba_ai-0.1.0.dist-info/METADATA
maliba_ai-0.1.0.dist-info/WHEEL
maliba_ai-0.1.0.dist-info/top_level.txt
maliba_ai-0.1.0.dist-info/RECORD
