Metadata-Version: 2.4
Name: maliba_ai
Version: 0.1.0
Summary: Bambara Text-to-Speech system using Maliba-AI models
Home-page: https://github.com/MALIBA-AI/bambara-tts
Author: Maliba-AI Engineering Team
Author-email: contact@maliba-ai.com
Project-URL: Bug Tracker, https://github.com/MALIBA-AI/bambara-tts/issues
Project-URL: Documentation, https://github.com/MALIBA-AI/bambara-tts/wiki
Project-URL: Source Code, https://github.com/MALIBA-AI/bambara-tts
Keywords: bambara,tts,text-to-speech,speech synthesis,maliba-ai,artificial intelligence,machine learning,natural language processing
Classifier: Development Status :: 3 - Alpha
Classifier: Intended Audience :: Developers
Classifier: Intended Audience :: Science/Research
Classifier: Topic :: Scientific/Engineering :: Artificial Intelligence
Classifier: Topic :: Multimedia :: Sound/Audio :: Speech
Classifier: License :: OSI Approved :: MIT License
Classifier: Programming Language :: Python :: 3
Classifier: Programming Language :: Python :: 3.8
Classifier: Programming Language :: Python :: 3.9
Classifier: Programming Language :: Python :: 3.10
Classifier: Programming Language :: Python :: 3.11
Classifier: Operating System :: OS Independent
Requires-Python: >=3.8
Requires-Dist: torch>=2.0.0
Requires-Dist: torchaudio>=2.0.0
Requires-Dist: transformers>=4.40.0
Requires-Dist: huggingface_hub>=0.20.0
Requires-Dist: librosa==0.11.0
Requires-Dist: soundfile==0.13.1
Requires-Dist: soxr==0.5.0.post1
Requires-Dist: einops==0.8.1
Requires-Dist: einx
Requires-Dist: omegaconf
Requires-Dist: numpy>=1.24.0
Requires-Dist: tqdm>=4.60.0
Requires-Dist: requests>=2.25.0
Requires-Dist: safetensors>=0.4.0
Requires-Dist: packaging>=20.0
Requires-Dist: unsloth==2025.6.1
Provides-Extra: full
Requires-Dist: unsloth; extra == "full"
Requires-Dist: bitsandbytes>=0.41.0; platform_system != "Darwin" and extra == "full"
Requires-Dist: triton<3.0.0,>=2.1.0; platform_system == "Linux" and extra == "full"
Requires-Dist: scipy>=1.10.0; extra == "full"
Requires-Dist: scikit-learn>=1.2.0; extra == "full"
Requires-Dist: numba>=0.56.0; extra == "full"
Requires-Dist: llvmlite>=0.39.0; extra == "full"
Requires-Dist: audioread>=3.0.0; extra == "full"
Requires-Dist: decorator>=5.1.0; extra == "full"
Requires-Dist: joblib>=1.2.0; extra == "full"
Requires-Dist: lazy_loader>=0.3.0; extra == "full"
Requires-Dist: pooch>=1.6.0; extra == "full"
Requires-Dist: regex>=2023.0.0; extra == "full"
Requires-Dist: filelock>=3.9.0; extra == "full"
Requires-Dist: fsspec>=2023.5.0; extra == "full"
Requires-Dist: tokenizers>=0.15.0; extra == "full"
Requires-Dist: PyYAML>=6.0; extra == "full"
Requires-Dist: typing_extensions>=4.5.0; extra == "full"
Requires-Dist: platformdirs>=3.0.0; extra == "full"
Requires-Dist: certifi>=2022.0.0; extra == "full"
Requires-Dist: charset_normalizer>=3.0.0; extra == "full"
Requires-Dist: idna>=3.4.0; extra == "full"
Requires-Dist: urllib3<3.0.0,>=1.26.0; extra == "full"
Requires-Dist: sympy>=1.12.0; extra == "full"
Requires-Dist: networkx>=3.0.0; extra == "full"
Requires-Dist: jinja2>=3.1.0; extra == "full"
Provides-Extra: unsloth
Requires-Dist: unsloth; extra == "unsloth"
Requires-Dist: bitsandbytes>=0.41.0; platform_system != "Darwin" and extra == "unsloth"
Requires-Dist: triton<3.0.0,>=2.1.0; platform_system == "Linux" and extra == "unsloth"
Provides-Extra: dev
Requires-Dist: ruff==0.11.4; extra == "dev"
Requires-Dist: isort==6.0.1; extra == "dev"
Requires-Dist: pre-commit==4.2.0; extra == "dev"
Requires-Dist: pytest>=7.0.0; extra == "dev"
Requires-Dist: black>=22.0.0; extra == "dev"
Requires-Dist: flake8>=4.0.0; extra == "dev"
Requires-Dist: mypy>=0.950; extra == "dev"
Provides-Extra: docs
Requires-Dist: sphinx>=4.0.0; extra == "docs"
Requires-Dist: sphinx-rtd-theme>=0.5.0; extra == "docs"
Dynamic: author
Dynamic: author-email
Dynamic: classifier
Dynamic: description
Dynamic: description-content-type
Dynamic: home-page
Dynamic: keywords
Dynamic: project-url
Dynamic: provides-extra
Dynamic: requires-dist
Dynamic: requires-python
Dynamic: summary
